conditionme/__init__.py
conditionme/completion/complete_model.py
conditionme/decision_gpt2_lm_head.py
conditionme/decision_gpt2_tokenize.py
conditionme/logger.py
conditionme/modify_forward_inputs.py
conditionme/reward_models/imdb_reward_model.py
conditionme/scaling/scaler.py
conditionme/statistics/calculate_distribution.py
conditionme/statistics/create_reward_table.py
conditionme/statistics/plot_dist_plot.py
conditionme/statistics/plotting.py
conditionme/type_check/utils.py
conditionme-0.0.3.dist-info/WHEEL
conditionme-0.0.3.dist-info/METADATA
conditionme-0.0.3.dist-info/RECORD
