Metadata-Version: 2.1
Name: conditionme
Version: 0.0.3
Summary: A library for finetuning language models via decision transformer / conditioning / upside-down reinforcement learning!
Home-page: https://github.com/thejaminator/conditionme
License: MIT
Author: James Chua
Author-email: chuajamessh@gmail.com
Requires-Python: >=3.8,<4.0
Classifier: License :: OSI Approved :: MIT License
Classifier: Programming Language :: Python :: 3
Classifier: Programming Language :: Python :: 3.8
Classifier: Programming Language :: Python :: 3.9
Classifier: Programming Language :: Python :: 3.10
Classifier: Programming Language :: Python :: 3.11
Classifier: Programming Language :: Python :: 3.8
Classifier: Programming Language :: Python :: 3.9
Requires-Dist: accelerate
Requires-Dist: datasets
Requires-Dist: matplotlib (>=3.5.3,<4.0.0)
Requires-Dist: pandas
Requires-Dist: scipy (>=1.10.0,<2.0.0)
Requires-Dist: seaborn (>=0.12.2,<0.13.0)
Requires-Dist: slist
Requires-Dist: torch (>=1.4.0,<2.0.0)
Requires-Dist: tqdm (>=4.62.0,<5.0.0)
Requires-Dist: transformers
Requires-Dist: typer
